MANIFEST.in
README.rst
requirements.txt
setup.cfg
setup.py
djmicrosip_tareas/__init__.py
djmicrosip_tareas/__init__.pyc
djmicrosip_tareas/config.pyc
djmicrosip_tareas/forms.pyc
djmicrosip_tareas/models.pyc
djmicrosip_tareas/tests.py
djmicrosip_tareas/tests.pyc
djmicrosip_tareas/urls.pyc
djmicrosip_tareas/views.pyc
djmicrosip_tareas.egg-info/PKG-INFO
djmicrosip_tareas.egg-info/SOURCES.txt
djmicrosip_tareas.egg-info/dependency_links.txt
djmicrosip_tareas.egg-info/requires.txt
djmicrosip_tareas.egg-info/top_level.txt
djmicrosip_tareas/herramientas/__init__.py
djmicrosip_tareas/herramientas/__init__.pyc
djmicrosip_tareas/herramientas/models.pyc
djmicrosip_tareas/herramientas/urls.pyc
djmicrosip_tareas/herramientas/views.pyc
djmicrosip_tareas/templates/djmicrosip_tareas/base.html
djmicrosip_tareas/templates/djmicrosip_tareas/index.html
djmicrosip_tareas/templates/djmicrosip_tareas/tarea.html
djmicrosip_tareas/templates/djmicrosip_tareas/tareas.html